smartinspectpython/__init__.py
smartinspectpython/siargumentnullexception.py
smartinspectpython/siargumentoutofrangeexception.py
smartinspectpython/siauto.py
smartinspectpython/sibinarycontext.py
smartinspectpython/sibinaryformatter.py
smartinspectpython/sibinaryviewercontext.py
smartinspectpython/sicolor.py
smartinspectpython/siconfiguration.py
smartinspectpython/siconfigurationtimer.py
smartinspectpython/siconnectionfoundeventargs.py
smartinspectpython/siconnectionsbuilder.py
smartinspectpython/siconnectionsparser.py
smartinspectpython/siconst.py
smartinspectpython/sicontrolcommand.py
smartinspectpython/sicontrolcommandeventargs.py
smartinspectpython/sicontrolcommandtype.py
smartinspectpython/sicryptostreamwriter.py
smartinspectpython/sidataviewercontext.py
smartinspectpython/sienumcomparable.py
smartinspectpython/sierroreventargs.py
smartinspectpython/sifilehelper.py
smartinspectpython/sifileprotocol.py
smartinspectpython/sifilerotate.py
smartinspectpython/sifilerotater.py
smartinspectpython/sifiltereventargs.py
smartinspectpython/siformatter.py
smartinspectpython/sigraphicid.py
smartinspectpython/sigraphicviewercontext.py
smartinspectpython/siinfoeventargs.py
smartinspectpython/siinspectorviewercontext.py
smartinspectpython/siinvalidconnectionsexception.py
smartinspectpython/silevel.py
smartinspectpython/silistviewercontext.py
smartinspectpython/siloadconfigurationexception.py
smartinspectpython/siloadconnectionsexception.py
smartinspectpython/silogentry.py
smartinspectpython/silogentryeventargs.py
smartinspectpython/silogentrytype.py
smartinspectpython/silogheader.py
smartinspectpython/silookuptable.py
smartinspectpython/simemoryprotocol.py
smartinspectpython/simethodparmlistcontext.py
smartinspectpython/siobjectrenderer.py
smartinspectpython/sioptionfoundeventargs.py
smartinspectpython/sioptionsparser.py
smartinspectpython/sipacket.py
smartinspectpython/sipacketqueue.py
smartinspectpython/sipacketqueueitem.py
smartinspectpython/sipackettype.py
smartinspectpython-3.0.38.dist-info/LICENSE
smartinspectpython-3.0.38.dist-info/METADATA
smartinspectpython-3.0.38.dist-info/WHEEL
smartinspectpython-3.0.38.dist-info/top_level.txt
smartinspectpython-3.0.38.dist-info/RECORD
