Metadata-Version: 2.2
Name: smartinspectpython
Version: 3.0.38
Summary: SmartInspect Python3 Library
Author: Todd Lucas
Author-email: <thlucas@yahoo.com>
Project-URL: Documentation, https://smartinspectpython.readthedocs.io/en/latest/__init__.html
Project-URL: GitHub, https://github.com/thlucas1/SmartInspectPython
Project-URL: Changelog, https://github.com/thlucas1/SmartInspectPython/blob/main/CHANGELOG.md
Project-URL: Issues, https://github.com/thlucas1/SmartInspectPython/issues
Keywords: python,smartinspect,logging,trace,tracing,debugging
Classifier: Development Status :: 5 - Production/Stable
Classifier: Intended Audience :: Developers
Classifier: Programming Language :: Python :: 3
Classifier: Operating System :: Microsoft :: Windows
Classifier: Operating System :: MacOS :: MacOS X
Classifier: Operating System :: Unix
Classifier: Topic :: Software Development
Classifier: Topic :: System :: Logging
Classifier: Natural Language :: English
Classifier: License :: OSI Approved :: MIT License
Requires-Python: >3.9.0
License-File: LICENSE
Requires-Dist: pycryptodome>=3.0
Requires-Dist: pywin32>=300; platform_system == "Windows"
Requires-Dist: watchdog>=6.0.0
Dynamic: author
Dynamic: author-email
Dynamic: classifier
Dynamic: description
Dynamic: description-content-type
Dynamic: keywords
Dynamic: project-url
Dynamic: requires-dist
Dynamic: requires-python
Dynamic: summary
